cnaclib/__init__.py
cnaclib/lSix.py
cnaclib/rac.py
cnaclib/rec_indemnite.py
cnaclib/tools.py
cnaclib-0.1.30.dist-info/licenses/LICENSE
cnaclib-0.1.30.dist-info/METADATA
cnaclib-0.1.30.dist-info/WHEEL
cnaclib-0.1.30.dist-info/top_level.txt
cnaclib-0.1.30.dist-info/RECORD
