Metadata-Version: 2.4
Name: cnaclib
Version: 0.1.30
Summary: Simulateur RAC
Author: BENHAMADA Nadir
Author-email: aistatendz@gmail.com
Keywords: cnac,tools
Classifier: Programming Language :: Python :: 3
Classifier: License :: OSI Approved :: MIT License
Classifier: Operating System :: OS Independent
Requires-Python: >=3.8
License-File: LICENSE
Requires-Dist: certifi>=2023.5.7
Requires-Dist: charset-normalizer>=3.1.0
Requires-Dist: idna>=3.4
Requires-Dist: numpy>=1.24.3
Requires-Dist: pandas>=2.0.1
Requires-Dist: python-dateutil>=2.8.2
Requires-Dist: pytz>=2023.3
Requires-Dist: six>=1.16.0
Requires-Dist: tzdata>=2023.3
Requires-Dist: urllib3>=2.0.2
Dynamic: author
Dynamic: author-email
Dynamic: classifier
Dynamic: description
Dynamic: description-content-type
Dynamic: keywords
Dynamic: license-file
Dynamic: requires-dist
Dynamic: requires-python
Dynamic: summary
